{
  "slug": "fresh-polish-cheese-pull-frittata--keto",
  "title": "Polish Frittata",
  "description": "A keto-friendly twist on a Polish classic, this frittata combines flavors from Eastern Europe with the richness of cheese.",
  "cuisine": "Polish",
  "diet": [
    "keto"
  ],
  "meal": "breakfast",
  "ingredients": [
    {
      "name": "6 large eggs",
      "amount": "6",
      "notes": "fresh eggs are best"
    },
    {
      "name": "1/4 cup grated cheese",
      "amount": "1/4 cup",
      "notes": "Polish cheese or cheddar work well"
    },
    {
      "name": "1/4 cup diced pull",
      "amount": "1/4 cup",
      "notes": "use lean meat for keto"
    },
    {
      "name": "1 tablespoon butter",
      "amount": "1",
      "notes": "unsalted"
    },
    {
      "name": "1 small onion, diced",
      "amount": "1 small",
      "notes": "add to taste"
    },
    {
      "name": "2 cloves garlic, minced",
      "amount": "2",
      "notes": "adds flavor"
    }
  ],
  "instructions": [
    "Preheat oven to 375°F (190°C).",
    "In a large skillet, melt butter over medium heat.",
    "Add diced onion and cook until softened, about 3-4 minutes.",
    "Add minced garlic and cook for an additional minute.",
    "Add diced pull and cook until browned, breaking up with a spoon as needed.",
    "In a large bowl, whisk together eggs and grated cheese.",
    "Pour egg mixture over cooked onion and pull mixture in skillet.",
    "Transfer skillet to preheated oven and bake for 15-20 minutes, or until eggs are set.",
    "Remove from oven and let cool for a few minutes.",
    "Slice into wedges and serve hot."
  ],
  "prepTimeMin": 10,
  "cookTimeMin": 20,
  "totalTimeMin": 30,
  "servings": 4,
  "difficulty": "easy",
  "tags": [
    "polish",
    "frittata",
    "keto"
  ],
  "source": "foodrecipes.page",
  "canonicalUrl": "https://foodrecipes.page/recipe/fresh-polish-cheese-pull-frittata--keto",
  "providerUsed": "groq",
  "createdAt": "2026-07-16T19:26:55.765Z"
}